llama_index/llms/openai/__init__.py
llama_index/llms/openai/base.py
llama_index/llms/openai/py.typed
llama_index/llms/openai/responses.py
llama_index/llms/openai/utils.py
llama_index_llms_openai-0.6.14.dist-info/METADATA
llama_index_llms_openai-0.6.14.dist-info/WHEEL
llama_index_llms_openai-0.6.14.dist-info/licenses/LICENSE
llama_index_llms_openai-0.6.14.dist-info/RECORD
