Metadata-Version: 2.4
Name: llama-index-llms-openai
Version: 0.6.14
Summary: llama-index llms openai integration
Author: llama-index
License-Expression: MIT
License-File: LICENSE
Requires-Python: <4.0,>=3.9
Requires-Dist: llama-index-core<0.15,>=0.14.5
Requires-Dist: openai<3,>=1.108.1
